FluidStack/__init__.py
FluidStack/client.py
FluidStack/configurations/__init__.py
FluidStack/configurations/client.py
FluidStack/core/__init__.py
FluidStack/core/api_error.py
FluidStack/core/client_wrapper.py
FluidStack/core/datetime_utils.py
FluidStack/core/file.py
FluidStack/core/http_client.py
FluidStack/core/jsonable_encoder.py
FluidStack/core/pydantic_utilities.py
FluidStack/core/query_encoder.py
FluidStack/core/remove_none_from_dict.py
FluidStack/core/request_options.py
FluidStack/environment.py
FluidStack/errors/__init__.py
FluidStack/errors/unauthorized_error.py
FluidStack/errors/unprocessable_entity_error.py
FluidStack/instances/__init__.py
FluidStack/instances/client.py
FluidStack/py.typed
FluidStack/ssh_keys/__init__.py
FluidStack/ssh_keys/client.py
FluidStack/templates/__init__.py
FluidStack/templates/client.py
FluidStack/types/__init__.py
FluidStack/types/configuration_instance_response.py
FluidStack/types/configuration_response.py
FluidStack/types/create_instance_response.py
FluidStack/types/entity_id.py
FluidStack/types/gpu_model_response.py
FluidStack/types/gpu_type.py
FluidStack/types/health_check_out_schema.py
FluidStack/types/http_validation_error.py
FluidStack/types/instance_response.py
FluidStack/types/instance_status.py
FluidStack/types/list_instance_response.py
FluidStack/types/message.py
FluidStack/types/operating_system_response.py
FluidStack/types/region.py
FluidStack/types/ssh_key_response.py
FluidStack/types/supported_operating_system.py
FluidStack/types/validation_error.py
FluidStack/types/validation_error_loc_item.py
FluidStack/types/volume_instance_response.py
FluidStack/types/volume_instance_response_input_cost_gb_hr.py
FluidStack/types/volume_status.py
FluidStack/version.py
fluidstack-0.0.8.dist-info/METADATA
fluidstack-0.0.8.dist-info/WHEEL
fluidstack-0.0.8.dist-info/RECORD
